gguf_io/__init__.py
gguf_io/__main__.py
gguf_io-0.0.3.dist-info/LICENSE
gguf_io-0.0.3.dist-info/WHEEL
gguf_io-0.0.3.dist-info/METADATA
gguf_io-0.0.3.dist-info/RECORD
