Metadata-Version: 2.1
Name: gguf-io
Version: 0.0.3
Summary: localhost for gguf.io (mirror)
Author-email: gguf <info@gguf.us>
Classifier: License :: OSI Approved :: MIT License
Project-URL: Repository, https://github.com/gguf-org/frontend
